tonelab/__init__.py
tonelab/clustering.py
tonelab/model.py
tonelab/tone2vec.py
tonelab/transcription.py
tonelab/utils.py
tonelab-0.2.data/data/requirements.txt
tonelab-0.2.dist-info/LICENSE.txt
tonelab-0.2.dist-info/METADATA
tonelab-0.2.dist-info/WHEEL
tonelab-0.2.dist-info/top_level.txt
tonelab-0.2.dist-info/RECORD
