Metadata-Version: 2.1
Name: tonelab
Version: 0.2
Summary: Platform designed for lightweight documentation and quantitative analysis in Sino-Tibetan tonal languages
Home-page: https://github.com/YiYang-github/ToneLab
Author: Yi Yang
Author-email: yanggnay@mail.ustc.edu.cn
Classifier: Development Status :: 4 - Beta
Classifier: Intended Audience :: Science/Research
Classifier: License :: OSI Approved :: MIT License
Classifier: Programming Language :: Python :: 3
Classifier: Topic :: Scientific/Engineering
Requires-Python: >=3.6
License-File: LICENSE.txt
Requires-Dist: asttokens==2.4.1
Requires-Dist: backcall==0.2.0
Requires-Dist: backports.tarfile==1.2.0
Requires-Dist: bottleneck==1.3.7
Requires-Dist: brotli==1.0.9
Requires-Dist: build==1.2.2
Requires-Dist: certifi==2024.8.30
Requires-Dist: cffi==1.17.1
Requires-Dist: charset-normalizer==3.3.2
Requires-Dist: comm==0.2.2
Requires-Dist: contourpy==1.0.5
Requires-Dist: cryptography==43.0.1
Requires-Dist: cycler==0.11.0
Requires-Dist: debugpy==1.6.7
Requires-Dist: decorator==5.1.1
Requires-Dist: docutils==0.20.1
Requires-Dist: et-xmlfile==1.1.0
Requires-Dist: executing==2.1.0
Requires-Dist: filelock==3.13.1
Requires-Dist: fonttools==4.51.0
Requires-Dist: gmpy2==2.1.2
Requires-Dist: idna==3.7
Requires-Dist: importlib-metadata==8.5.0
Requires-Dist: importlib-resources==6.4.0
Requires-Dist: ipykernel==6.29.5
Requires-Dist: ipython==8.12.2
Requires-Dist: jaraco.classes==3.4.0
Requires-Dist: jaraco.context==6.0.1
Requires-Dist: jaraco.functools==4.1.0
Requires-Dist: jedi==0.19.1
Requires-Dist: jeepney==0.8.0
Requires-Dist: Jinja2==3.1.4
Requires-Dist: joblib==1.4.2
Requires-Dist: jupyter-client==8.6.3
Requires-Dist: jupyter-core==5.7.2
Requires-Dist: keyring==25.4.1
Requires-Dist: kiwisolver==1.4.4
Requires-Dist: llvmlite==0.41.1
Requires-Dist: markdown-it-py==3.0.0
Requires-Dist: MarkupSafe==2.1.3
Requires-Dist: matplotlib==3.7.2
Requires-Dist: matplotlib-inline==0.1.7
Requires-Dist: mdurl==0.1.2
Requires-Dist: mkl-fft==1.3.8
Requires-Dist: mkl-random==1.2.4
Requires-Dist: mkl-service==2.4.0
Requires-Dist: more-itertools==10.5.0
Requires-Dist: mpmath==1.3.0
Requires-Dist: nest-asyncio==1.6.0
Requires-Dist: networkx==3.1
Requires-Dist: nh3==0.2.18
Requires-Dist: numba==0.58.1
Requires-Dist: numexpr==2.8.4
Requires-Dist: numpy==1.24.3
Requires-Dist: openpyxl==3.1.5
Requires-Dist: packaging==24.1
Requires-Dist: pandas==2.0.3
Requires-Dist: parso==0.8.4
Requires-Dist: pexpect==4.9.0
Requires-Dist: pickleshare==0.7.5
Requires-Dist: pillow==10.3.0
Requires-Dist: pkginfo==1.10.0
Requires-Dist: platformdirs==4.3.6
Requires-Dist: ply==3.11
Requires-Dist: pooch==1.7.0
Requires-Dist: prompt-toolkit==3.0.48
Requires-Dist: psutil==6.0.0
Requires-Dist: ptyprocess==0.7.0
Requires-Dist: pure-eval==0.2.3
Requires-Dist: pycparser==2.22
Requires-Dist: Pygments==2.18.0
Requires-Dist: pynndescent==0.5.13
Requires-Dist: pyparsing==3.0.9
Requires-Dist: pyproject-hooks==1.2.0
Requires-Dist: PyQt5==5.15.10
Requires-Dist: PyQt5-sip==12.13.0
Requires-Dist: PySocks==1.7.1
Requires-Dist: python-dateutil==2.9.0
Requires-Dist: pytz==2024.1
Requires-Dist: PyYAML==6.0.1
Requires-Dist: pyzmq==25.1.2
Requires-Dist: readme-renderer==43.0
Requires-Dist: requests==2.32.3
Requires-Dist: requests-toolbelt==1.0.0
Requires-Dist: rfc3986==2.0.0
Requires-Dist: rich==13.9.1
Requires-Dist: scikit-learn==1.3.0
Requires-Dist: scipy==1.10.1
Requires-Dist: SecretStorage==3.3.3
Requires-Dist: sip==6.7.12
Requires-Dist: six==1.16.0
Requires-Dist: stack-data==0.6.2
Requires-Dist: sympy==1.13.2
Requires-Dist: threadpoolctl==3.5.0
Requires-Dist: tomli==2.0.1
Requires-Dist: torch==2.4.1
Requires-Dist: torchaudio==2.4.1
Requires-Dist: torchvision==0.19.1
Requires-Dist: tornado==6.4.1
Requires-Dist: tqdm==4.66.5
Requires-Dist: traitlets==5.14.3
Requires-Dist: triton==3.0.0
Requires-Dist: twine==5.1.1
Requires-Dist: typing-extensions==4.12.2
Requires-Dist: tzdata==2023.3
Requires-Dist: umap-learn==0.5.6
Requires-Dist: unicodedata2==15.1.0
Requires-Dist: urllib3==2.2.2
Requires-Dist: wcwidth==0.2.13
Requires-Dist: zipp==3.20.2
